patchtool/Fake.py
patchtool/PatchMgr.py
patchtool/__init__.py
patchtool/main.py
patchtool/test.py
patchtool-1.2.0.post1.dist-info/LICENSE
patchtool-1.2.0.post1.dist-info/METADATA
patchtool-1.2.0.post1.dist-info/WHEEL
patchtool-1.2.0.post1.dist-info/entry_points.txt
patchtool-1.2.0.post1.dist-info/top_level.txt
patchtool-1.2.0.post1.dist-info/RECORD
