Metadata-Version: 2.1
Name: patchtool
Version: 1.2.0.post1
Summary: Converting patches of old version to the ones with current line number
Home-page: https://github.com/HsimWong/patchtool
Author: Xin WANG
Author-email: hsimwong1202@gmail.com
License: UNKNOWN
Platform: UNKNOWN
Classifier: Programming Language :: Python :: 3
Classifier: License :: OSI Approved :: GNU General Public License v3 (GPLv3)
Classifier: Operating System :: OS Independent
